{"nodes": [{"id": "c_users_vinita_desktop_projects_jarvis_tests_test_registry_cpp", "label": "test_registry.cpp", "file_type": "code", "source_file": "tests/test_registry.cpp", "source_location": "L1"}, {"id": "c_users_vinita_desktop_projects_jarvis_tests_test_registry_trivial", "label": "trivial()", "file_type": "code", "source_file": "tests/test_registry.cpp", "source_location": "L9", "_callable": true}, {"id": "toolptr", "label": "ToolPtr", "file_type": "code", "source_file": "", "source_location": "", "origin_file": "C:\\Users\\Vinita\\Desktop\\Projects\\Jarvis\\tests\\test_registry.cpp"}, {"id": "string", "label": "string", "file_type": "code", "source_file": "", "source_location": "", "origin_file": "C:\\Users\\Vinita\\Desktop\\Projects\\Jarvis\\tests\\test_registry.cpp"}], "edges": [{"source": "c_users_vinita_desktop_projects_jarvis_tests_test_registry_cpp", "target": "doctest", "relation": "imports", "context": "import", "confidence": "EXTRACTED", "source_file": "tests/test_registry.cpp", "source_location": "L1", "weight": 1.0}, {"source": "c_users_vinita_desktop_projects_jarvis_tests_test_registry_cpp", "target": "tool", "relation": "imports", "context": "import", "confidence": "EXTRACTED", "source_file": "tests/test_registry.cpp", "source_location": "L3", "weight": 1.0}, {"source": "c_users_vinita_desktop_projects_jarvis_tests_test_registry_cpp", "target": "tool_registry", "relation": "imports", "context": "import", "confidence": "EXTRACTED", "source_file": "tests/test_registry.cpp", "source_location": "L4", "weight": 1.0}, {"source": "c_users_vinita_desktop_projects_jarvis_tests_test_registry_cpp", "target": "c_users_vinita_desktop_projects_jarvis_tests_test_registry_trivial", "relation": "contains", "confidence": "EXTRACTED", "source_file": "tests/test_registry.cpp", "source_location": "L9", "weight": 1.0}, {"source": "c_users_vinita_desktop_projects_jarvis_tests_test_registry_trivial", "target": "toolptr", "relation": "references", "confidence": "EXTRACTED", "source_file": "tests/test_registry.cpp", "source_location": "L9", "weight": 1.0, "context": "return_type"}, {"source": "c_users_vinita_desktop_projects_jarvis_tests_test_registry_trivial", "target": "string", "relation": "references", "confidence": "EXTRACTED", "source_file": "tests/test_registry.cpp", "source_location": "L9", "weight": 1.0, "context": "parameter_type"}], "raw_calls": [{"caller_nid": "c_users_vinita_desktop_projects_jarvis_tests_test_registry_trivial", "callee": "makeTool", "is_member_call": false, "source_file": "C:\\Users\\Vinita\\Desktop\\Projects\\Jarvis\\tests\\test_registry.cpp", "source_location": "L10", "receiver": null, "lang": "cpp"}]}